setup.py
salure_helpers/mandrill/__init__.py
salure_helpers/mandrill/mail_client.py
salure_helpers/mandrill/templates/mail_salureconnect.html
salure_helpers_mandrill.egg-info/PKG-INFO
salure_helpers_mandrill.egg-info/SOURCES.txt
salure_helpers_mandrill.egg-info/dependency_links.txt
salure_helpers_mandrill.egg-info/not-zip-safe
salure_helpers_mandrill.egg-info/requires.txt
salure_helpers_mandrill.egg-info/top_level.txt