Metadata-Version: 1.0
Name: salure-helpers-mandrill
Version: 1.0.1
Summary: Mandrill wrapper from Salure
Home-page: UNKNOWN
Author: D&A Salure
Author-email: support@salureconnnect.com
License: Salure License
Platform: UNKNOWN
